[
  {
    "id": 5500,
    "name": "osm_r_sampled",
    "type": "STANDARD",
    "description": "origin shield monitoring for r lines",
    "aggregationInSeconds": 60,
    "purgeIntervalInDays": 7,
    "maxQueryDurationInMinutes": 120,
    "reportType": "",
    "dimensions": [
      {
        "id": 5504,
        "name": "Format",
        "description": "Delivery format of the stream.",
        "helpText": "Format",
        "dataType": "STRING",
        "group": [
          {
            "id": -1,
            "name": "OTHERS",
            "description": "OTHERS"
          }
        ]
      },
      {
        "id": 5505,
        "name": "CDN",
        "description": "Name of the CDN provider.",
        "helpText": "CDN",
        "dataType": "STRING",
        "group": [
          {
            "id": -1,
            "name": "OTHERS",
            "description": "OTHERS"
          }
        ]
      }
    ],
    "metrics": [
      {
        "id": 5520,
        "name": "Hits",
        "type": "COUNT",
        "description": "Total number of requests.",
        "group": [
          {
            "id": -1,
            "name": "OTHERS",
            "description": "OTHERS"
          }
        ]
      },
      {
        "id": 5521,
        "name": "Hits/sec",
        "type": "COUNT",
        "description": "Number of hits per second.",
        "group": [
          {
            "id": -1,
            "name": "OTHERS",
            "description": "OTHERS"
          }
        ]
      }
    ]
  }
]
