{
  "rows": [
    [
      "196305",
      "cbsnewsFusion",
      "306714",
      "481.066667",
      "3.8"
    ],
    [
      "682874",
      "KPIX3_ULS",
      "219526",
      "2.02",
      "4.6"
    ]
  ],
  "metaData": {
    "startTimeInEpoch": 1551432600,
    "offset": 0,
    "limit": 10000,
    "timeZone": "GMT",
    "hasMoreData": false,
    "dataStore": null,
    "aggregation": 300,
    "endTimeInEpoch": 1551432900
  },
  "columns": [
    {
      "type": "dimension",
      "name": "Stream ID",
      "description": "Unique identifier associated with a stream generated by the Akamai provisioning workflow.",
      "index": 0
    },
    {
      "type": "dimension",
      "name": "Stream Name",
      "description": "Name associated with a stream generated by the Akamai provisioning workflow for Stream Packaging",
      "index": 1
    },
    {
      "type": "dimension",
      "name": "CP Code",
      "description": "Content Provider Code (CPCode) is an identifier assigned to a contract and used for reporting, billing and monitoring traffic served.",
      "index": 2
    },
    {
      "type": "metric",
      "name": "Viewers",
      "id": 12053,
      "description": "Viewers for Delivery",
      "index": 3,
      "aggregate": "1961.62",
      "dataType": "count"
    },
    {
      "type": "metric",
      "name": "Egress Bit Rate",
      "id": 12052,
      "description": "Bit Rate Delivered",
      "index": 4,
      "aggregate": "1027.96",
      "unit": "Mbps",
      "dataType": "bandwidth"
    }
  ]
}