{
  "accountId": "act_A-CCT1234",
  "contractId": "ctr_C-0N7RAC71",
  "groupId": "grp_12345",
  "includeId": "inc_173136",
  "includeName": "my.new.include.com",
  "includeType": "MICROSERVICES",
  "includeVersion": 3,
  "etag": "a9dfe78cf93090516bde891d009eaf57",
  "ruleFormat": "v2022-10-18",
  "rules": {
    "name": "default",
    "criteria": [],
    "children": [],
    "options": {
      "is_secure": false
    },
    "behaviors": [
      {
        "name": "origin",
        "options": {
          "httpPort": 80,
          "enableTrueClientIp": false,
          "compress": true,
          "cacheKeyHostname": "ORIGIN_HOSTNAME",
          "forwardHostHeader": "REQUEST_HOST_HEADER",
          "hostname": "origin.com",
          "originType": "CUSTOMER"
        }
      },
      {
        "name": "cpCode",
        "options": {
          "value": {
            "id": 12345,
            "name": "my CP code"
          }
        }
      }
    ]
  }
}