{
  "itemKind": "IMAGECOLLECTION",
  "items": [
    {
      "id": "ring_spin360",
      "definition": {
        "items": [
          {
            "type": "spin360",
            "urls": [
              "https://example.com/img/ring_01.jpg",
              "https://example.com/img/ring_02.jpg",
              "https://example.com/img/ring_03.jpg",
              "https://example.com/img/ring_04.jpg",
              "https://example.com/img/ring_05.jpg",
              "https://example.com/img/ring_06.jpg",
              "https://example.com/img/ring_07.jpg",
              "https://example.com/img/ring_08.jpg",
              "https://example.com/img/ring_09.jpg",
              "https://example.com/img/ring_10.jpg",
              "https://example.com/img/ring_11.jpg",
              "https://example.com/img/ring_12.jpg",
              "https://example.com/img/ring_13.jpg",
              "https://example.com/img/ring_14.jpg",
              "https://example.com/img/ring_15.jpg",
              "https://example.com/img/ring_16.jpg",
              "https://example.com/img/ring_17.jpg",
              "https://example.com/img/ring_18.jpg",
              "https://example.com/img/ring_19.jpg",
              "https://example.com/img/ring_20.jpg"
            ]
          },
          {
            "type": "video",
            "url": "https://example.com/video/engagement.mp4",
            "poster": "",
            "mime": "video/mp4"
          }
        ]
      },
      "user": "jsmith",
      "lastModifiedTimestamp": 1649865301693
    },
    {
      "id": "SKU-26684355",
      "description": "A collection for bikes",
      "definition": {
        "version": 1,
        "items": [
          {
            "type": "image",
            "url": "https://example.com/bikes/sport-bike.jpg",
            "tags": [
              "red"
            ],
            "mime": "image/jpeg"
          },
          {
            "type": "image",
            "url": "https://example.com/bikes/road-bike.jpg",
            "tags": [
              "blue"
            ],
            "mime": "image/jpeg"
          },
          {
            "type": "image",
            "url": "https://example.com/bikes/transport-bike.jpg",
            "tags": [
              "red"
            ],
            "mime": "image/jpeg"
          }
        ]
      },
      "user": "jsmith",
      "lastModifiedTimestamp": 1649865078032
    }
  ],
  "totalItems": 2
}