{
  "onboardingId": 101,
  "onboardingLink": "/appsec/v1/onboardings/101",
  "accountId": "A-CCT1234",
  "contractId": "C-0N7RAC7",
  "groupId": 54321,
  "product": "ASM",
  "hostnames": [
    "www.example.com",
    "www.example.net"
  ],
  "onboardingStatus": "CREATED",
  "settings": {
    "delivery": {
      "origins": [
        {
          "hostname": "www.example.com",
          "origin": "origin-ea0ac1-www.example.com"
        },
        {
          "hostname": "www.example.net",
          "origin": "origin-8eeeba-www.example.net"
        }
      ]
    },
    "certificate": {
      "certificateType": "CUSTOM_EXISTING",
      "adminContact": {
        "firstName": "AdminUser",
        "lastName": "User",
        "phone": "+9180460018",
        "email": "adminContact@nomail-akamai.com"
      },
      "commonName": "www.at.konaqa.com",
      "enrollmentId": 94723,
      "enrollmentLink": "/cps/v2/enrollments/94723"
    },
    "security": {
      "configType": "EXISTING",
      "policyType": "EXISTING",
      "configId": 243359,
      "configName": "sec-config",
      "configLink": "/appsec/v1/configs/12345",
      "cloneVersion": 25,
      "policyId": "PLCY_12344",
      "policyLink": "/appsec/v1/configs/12345/versions/25/security-policies/PLCY_12345",
      "evalRequired": true,
      "policyName": "sec-policy",
      "protections": {
        "applyApplicationLayerControls": true,
        "applyBotmanControls": false,
        "applyNetworkLayerControls": true,
        "applyRateControls": true,
        "applyReputationControls": true,
        "applySlowPostControls": true
      }
    },
    "settingsLink": "/appsec/v1/onboardings/101/settings"
  },
  "activations": [
    {
      "activationId": 105,
      "activationStatus": "ACTIVE",
      "network": "STAGING",
      "createdDate": "2024-05-03T10:38:21Z",
      "completedDate": "2024-05-03T12:34:21Z",
      "activationLink": "/appsec/v1/onboardings/101/activations/105"
    },
    {
      "activationId": 106,
      "activationStatus": "ACTIVE",
      "network": "PRODUCTION",
      "createdDate": "2024-05-04T10:38:21Z",
      "completedDate": "2024-05-04T12:34:21Z",
      "activationLink": "/appsec/v1/onboardings/101/activations/106"
    }
  ],
  "currentStep": 3,
  "totalSteps": 5,
  "nextSteps": [
    {
      "stepName": "certificate-validation",
      "stepDescription": "Validate the certificate challenge",
      "stepLink": "/appsec/v1/onboardings/101/certificate-validation"
    },
    {
      "stepName": "origin-validation",
      "stepDescription": "Validate that the origin is live",
      "stepLink": "/appsec/v1/onboardings/101/origin-validation"
    }
  ],
  "createdBy": "hgildong",
  "createdDate": "2024-05-02T22:08:50Z",
  "modifiedBy": "jsmith",
  "modifiedDate": "2024-05-04T12:34:21Z"
}
